[
  {
    "id": 1,
    "categoria": ["Balcões", "Caixas"],
    "nome": "BALCÃO CAIXINHA",
    "preco": 449.00,
    "tamanho": "1.10m",
    "dimensoes": "1.10/1.00m Altura x 55cm Largura x 40cm Profundidade",
    "img": "./images/cards/balcaoCaixaComRodape.jpg",
    "descricao": "Balcão compacto com rodapé e gaveta. Ideal para otimizar espaços pequenos com baixo custo.",
    "tags": ["balcao", "balcoes", "caixa", "rodape", "atendimento", "compacto", "gaveta", "movel", "moveis"]
  },
  {
    "id": 2,
    "categoria": ["Balcões", "Caixas", "Vitrines", "Farmácia"],
    "nome": "BALCÃO CAIXA COM VITRINE (BRANCO)",
    "preco": 815.00,
    "tamanho": "1.10m",
    "dimensoes": "1.10/1.00m Altura x 1.15m Largura x 40cm Profundidade",
    "img": "./images/cards/balcaoCaixaComVitrineBranco.jpg",
    "descricao": "O campeão de vendas: balcão caixa com ampla vitrine frontal. Perfeito para Farmácias e Lojas variadas.",
    "tags": ["balcao", "balcoes", "caixa", "vitrine", "branco", "atendimento", "farmacia", "vidro", "expositor", "movel", "moveis"]
  },
  {
    "id": 3,
    "categoria": ["Balcões", "Vitrines", "Farmácia", "Expositores"],
    "nome": "BALCÃO VITRINE",
    "preco": 800.00,
    "tamanho": "1.00m",
    "dimensoes": "1.00m Altura x 1.00m Largura x 40cm Profundidade",
    "img": "./images/cards/balcaoVitrine.jpg",
    "descricao": "Vitrine expositora com opção de prateleiras em MDF ou Vidro. Essencial para exibir medicamentos ou joias.",
    "tags": ["balcao", "balcoes", "vitrine", "vidro", "prateleira", "farmacia", "medicamento", "joia", "expositor", "movel", "moveis"]
  },
  {
  "id": 4,
  "categoria": ["Balcões", "Caixas"],
  "nome": "BALCÃO CAIXA",
  "preco": 815.00,
  "tamanho": "1.10m",
  "dimensoes": "1.10/1.00m Altura x 1.00m Largura x 40cm Profundidade",
  "img": "./images/cards/balcaoCaixa.jpg",
  "descricao": "Balcão de atendimento fechado, focado em segurança e organização interna para o operador.",
  "tags": ["balcao", "balcoes", "caixa", "atendimento", "fechado", "seguranca", "simples", "movel", "moveis"]
  },
  {
    "id": 5,
    "categoria": ["Colmeias", "Expositores", "Armários", "Pet Shop"],
    "nome": "ARMÁRIO COLMEIA",
    "preco": 699.00,
    "tamanho": "1.85m",
    "dimensoes": "1.85m Altura x 90cm Largura x 30cm Profundidade",
    "img": "./images/cards/armarioColmeia.jpg",
    "descricao": "Expositor vertical com nichos. Ótimo para Pet Shops (rações/acessórios) e lojas de roupas.",
    "tags": ["armario", "colmeia", "nicho", "nichos", "estante", "expositor", "pet shop", "roupa", "camiseta", "movel", "moveis"]
  },
  {
  "id": 6,
  "categoria": ["Expositores", "Prateleiras", "Móvel", "Movel", "Moveis"],
  "nome": "MÓVEL COM PRATELEIRAS",
  "preco": 560.00,
  "tamanho": "1.80m",
  "dimensoes": "1.80m Altura x 90cm Largura x 30cm Profundidade",
  "img": "./images/cards/movelPrateleira.jpg",
  "galeria": [
    "./images/movelprat (1).jpeg",
    "./images/movelprat (2).jpeg",
    "./images/movelprat (3).jpeg"
  ],
  "descricao": "Estante versátil com prateleiras abertas. Item obrigatório para Farmácias e Pet Shops.\n\nAltura: 1.80m\nLargura: 90cm\nProfundidade: 30cm.",
  "tags": ["movel", "moveis", "estante", "prateleira", "prateleiras", "gondola", "farmacia", "pet shop", "aberto"]
  },
  {
    "id": 7,
    "categoria": ["Araras", "Colmeias", "Expositores"],
    "nome": "ARARA DE MDF COM COLMEIA",
    "preco": 459.00,
    "tamanho": "1.85m",
    "dimensoes": "1.85m Altura x 90cm Largura x 30cm Profundidade",
    "img": "./images/cards/araraMDFColmeia.jpg",
    "descricao": "Modelo híbrido com cabideiro superior e nichos na base, aproveitando 100% do espaço vertical.",
    "tags": ["arara", "araras", "mdf", "colmeia", "cabideiro", "cabide", "nicho", "nichos", "roupa", "loja", "movel", "moveis"]
  },
  {
  "id": 8,
  "categoria": ["Araras", "Colmeias", "Expositores"],
  "nome": "ARARA DE MDF COM COLMEIA LATERAL",
  "preco": 459.00,
  "tamanho": "1.80m",
  "dimensoes": "1.80m Altura x 90cm Largura x 30cm Profundidade",
  "img": "./images/cards/araraMDFColmeia2.jpg",
  "galeria": [
    "./images/nicholat (1).jpeg",
    "./images/nicholat (2).jpeg",
    "./images/nicholat (3).jpeg",
    "./images/nicholat (4).jpeg"
  ],
  "descricao": "Modelo premium com coluna lateral de nichos. Organização completa para looks e acessórios.\n\nAltura: 1.80m\nLargura: 90cm\nProfundidade: 30cm.",
  "tags": ["arara", "araras", "mdf", "colmeia", "lateral", "cabideiro", "cabide", "nicho", "premium", "roupa", "loja", "movel", "moveis"]
  },
  {
    "id": 9,
    "categoria": ["Balcões", "Caixas", "Vitrines", "Linha Premium"],
    "nome": "BALCÃO CAIXA COM VITRINE (PRETO)",
    "preco": 910.00,
    "tamanho": "1.10m",
    "dimensoes": "1.10/1.00m Altura x 1.15m Largura x 40cm Profundidade",
    "img": "./images/cards/balcaoCaixaComVitrinePreto.jpg",
    "descricao": "Acabamento sofisticado na cor preta, ideal para boutiques e lojas modernas.",
    "tags": ["balcao", "balcoes", "caixa", "vitrine", "preto", "escura", "atendimento", "premium", "boutique", "movel", "moveis"]
  },
  {
  "id": 10,
  "categoria": ["Gôndolas", "Expositores", "Móveis de Centro", "Moveis"],
  "nome": "GÔNDOLA 8 CANTOS",
  "preco": 899.00,
  "tamanho": "1.20m",
  "dimensoes": "1.20m Altura x 90cm Largura x 90cm Profundidade",
  "img": "./images/8cantos (3).jpeg",
  "galeria": [
    "./images/8cantos (1).jpeg"
  ],
  "descricao": "Gôndola central de 8 cantos em MDF, ideal para exposição de produtos no centro da loja, com ótimo aproveitamento de espaço e visual organizado.\n\nAltura: 1.20m\nLargura: 90cm\nProfundidade: 90cm.",
  "tags": ["gondola", "gondolas", "8 cantos", "central", "mdf", "expositor", "movel de centro", "moveis", "loja", "bazar", "conveniencia", "farmacia"]
   },
    {
    "id": 11,
    "categoria": ["Gôndolas", "Expositores", "Móveis de Centro", "Moveis"],
    "nome": "GÔNDOLA CENTRAL",
    "preco": 990.00,
    "tamanho": "1.20m",
    "dimensoes": "1.20m Altura x 1.40m Largura x 80cm Profundidade",
    "img": "./images/gondoval (1).jpeg",
    "galeria": [
      "./images/gondoval (3).jpeg",
      "./images/gondoval (4).jpeg"
    ],
    "descricao": "Gôndola central em MDF, ideal para exposição de produtos no centro da loja, aproveitando bem o espaço e melhorando a visualização dos itens.\n\nAltura: 1.20m\nLargura: 1.40m\nProfundidade: 80cm.",
    "tags": ["gondola", "gondolas", "central", "mdf", "expositor", "movel de centro", "moveis", "loja", "bazar", "conveniencia", "farmacia"]
  },
  {
  "id": 12,
  "categoria": ["Expositores", "Móveis para Vitrine", "Moveis", "Vitrines"],
  "nome": "MÓVEL PARA VITRINE",
  "preco": 1590.00,
  "tamanho": "1.10m",
  "dimensoes": "1.10m Altura x 1.50m Largura",
  "img": "./images/vitmad (1).jpeg",
  "galeria": [
    "./images/vitmad (3).jpeg",
    "./images/vitmad (4).jpeg"
  ],
  "descricao": "Móvel para vitrine em MDF, ideal para destacar produtos com visual moderno e exposição em níveis.\n\nAltura: 1.10m\nLargura: 1.50m",
  "tags": ["movel", "moveis", "vitrine", "movel para vitrine", "mdf", "expositor", "loja", "bazar", "roupa", "calcado", "mostruario"]
  },
  {
  "id": 13,
  "categoria": ["Armários", "Vestiário", "Expositores", "Moveis"],
  "nome": "ARMÁRIO VESTIÁRIO 8 PORTAS",
  "preco": 1040.00,
  "tamanho": "1.80m",
  "dimensoes": "1.80m Altura x 60cm Largura x 30cm Profundidade",
  "img": "./images/8P (1).jpeg",
  "galeria": [
    "./images/8P (2).jpeg",
    "./images/V-vestiarios.mp4"
  ],
  "descricao": "Armário vestiário em MDF com 8 portas, ideal para organização de pertences em lojas, fábricas e ambientes de apoio. Cada porta acompanha 2 chaves.\n\nAltura: 1.80m\nLargura: 60cm\nProfundidade: 30cm.",
  "tags": ["armario", "vestiario", "8 portas", "mdf", "portas", "chave", "organizacao", "loja", "fabrica", "movel", "moveis"]
},
  {
  "id": 14,
  "categoria": ["Gôndolas", "Painel Canaletado", "Expositores", "Moveis"],
  "nome": "GÔNDOLA CANALETADA",
  "preco": 490.00,
  "tamanho": "1.10m",
  "dimensoes": "1.10m Altura x 90cm Largura x 60cm Profundidade",
  "img": "./images/gondolapaine (2).jpeg",
  "descricao": "Gôndola canaletada em MDF, ideal para exposição de produtos com uso de ganchos e acessórios, trazendo organização e aproveitamento inteligente do espaço.\n\nAltura: 1.10m\nLargura: 90cm\nProfundidade: 60cm.",
  "tags": ["gondola", "gondolas", "caneletada", "canaletada", "painel canaletado", "mdf", "expositor", "gancho", "loja", "bazar", "conveniencia", "farmacia"]
 },
  {
  "id": 15,
  "categoria": ["Gôndolas", "Expositores", "Móveis de Centro", "Moveis"],
  "nome": "GÔNDOLA QUADRADA MADEIRADA",
  "preco": 1590.00,
  "tamanho": "1.20m",
  "dimensoes": "1.20m Altura x 90cm Largura x 90cm Profundidade",
  "img": "./images/quadradaMad (2).jpeg",
  "descricao": "Gôndola quadrada madeirada em MDF, com prateleiras engrossuradas, ideal para exposição de produtos no centro da loja com visual mais robusto e sofisticado.\n\nAltura: 1.20m\nLargura: 90cm\nProfundidade: 90cm.",
  "tags": ["gondola", "gondolas", "quadrada", "madeirada", "mdf", "prateleiras engrossuradas", "movel de centro", "expositor", "loja", "bazar", "conveniencia", "farmacia"]
 },
  {
  "id": 16,
  "categoria": ["Balcões", "Caixas", "Recepção", "Linha Premium"],
  "nome": "BALCÃO CAIXA COM RIPADO",
  "preco": 3750.00,
  "tamanho": "1.00m",
  "dimensoes": "2.50m Comprimento x 1.20m Parte do L x 1.00m Altura x 40cm Profundidade",
  "img": "./images/cxripado (2).jpeg",
  "galeria": [
    "./images/cxripado (1).jpeg",
    "./images/cxripado (3).jpeg",
    "./images/cxripado (4).jpeg"
  ],
  "descricao": "Balcão de recepção em L com detalhe ripado e iluminação em LED, ideal para lojas e ambientes que buscam um visual mais sofisticado e moderno.\n\nComprimento: 2.50m\nParte do L: 1.20m\nAltura: 1.00m\nProfundidade: 40cm.",
  "tags": ["balcao", "balcoes", "caixa", "recepcao", "ripado", "led", "balcao em l", "premium", "atendimento", "loja", "movel", "moveis"]
 },
 {
  "id": 17,
  "categoria": ["Expositores", "Móveis de Apoio", "Moveis"],
  "nome": "CARRINHO AUXILIAR",
  "preco": 389.00,
  "tamanho": "80cm",
  "dimensoes": "80cm Altura x 40cm Largura x 30cm Profundidade",
  "img": "./images/carrinho (4).jpeg",
  "galeria": [
    "./images/carrinho (1).jpeg",
    "./images/carrinho (3).jpeg",
    "./images/carrinho (4).jpeg"
  ],
  "descricao": "Carrinho auxiliar em MDF, ideal para apoiar produtos e organizar o atendimento com praticidade no dia a dia da loja.\n\nAltura: 80cm\nLargura: 40cm\nProfundidade: 30cm.",
  "tags": ["carrinho", "auxiliar", "movel de apoio", "mdf", "organizador", "expositor", "loja", "movel", "moveis"]
 },
 {
  "id": 18,
  "categoria": ["Expositores", "Móveis para Vitrine", "Moveis", "Vitrines"],
  "nome": "MÓVEL PARA VITRINE EM S",
  "preco": 689.00,
  "tamanho": "1.80m",
  "dimensoes": "1.80m Altura x 90cm Largura x 30cm Profundidade",
  "img": "./images/VIT (3).jpg",
  "galeria": [
    "./images/VIT (1).jpg",
    "./images/VIT (2).jpg",
    "./images/VIT (3).jpg",
    "./images/VIT (4).jpg"
  ],
  "descricao": "Móvel para vitrine em S, ideal para destacar produtos com exposição organizada e visual moderno.\n\nAltura: 1.80m\nLargura: 90cm\nProfundidade: 30cm.",
  "tags": ["movel", "moveis", "vitrine", "vitrine em s", "mdf", "expositor", "loja", "mostruario"]
 }
,
 {
  "id": 19,
  "categoria": ["Expositores", "Prateleiras", "Moveis"],
  "nome": "MÓVEL PRATELEIRA INCLINADA",
  "preco": 629.00,
  "tamanho": "1.80m",
  "dimensoes": "1.80m Altura x 90cm Largura x 30cm Profundidade",
  "img": "./images/prat (2).jpeg",
  "galeria": [
    "./images/prat (2).jpeg",
    "./images/prat (3).jpeg",
    "./images/prat (1).jpeg"
  ],
  "descricao": "Móvel com prateleiras inclinadas, ideal para exposição prática e organizada de produtos no dia a dia da loja.\n\nAltura: 1.80m\nLargura: 90cm\nProfundidade: 30cm.",
  "tags": ["movel", "moveis", "prateleira", "prateleiras inclinadas", "expositor", "mdf", "loja", "organizador"]
 }
,
 {
  "id": 20,
  "categoria": ["Expositores", "Móveis de Apoio", "Moveis"],
  "nome": "MÓVEL ESCADA",
  "preco": 240.00,
  "tamanho": "90cm",
  "dimensoes": "90cm Altura x 90cm Largura x 30cm Profundidade",
  "img": "./images/escadinha (2).jpeg",
  "galeria": [
    "./images/escadinha (2).jpeg",
    "./images/escadinha (1).jpeg"
  ],
  "descricao": "Móvel escada em MDF, ideal para exposição de produtos com visual prático e organizado em diferentes setores da loja.\n\nAltura: 90cm\nLargura: 90cm\nProfundidade: 30cm.",
  "tags": ["movel", "moveis", "escada", "escadinha", "expositor", "mdf", "loja", "organizador"]
 }
,
 {
  "id": 21,
  "categoria": ["Expositores", "Painel Canaletado", "Moveis"],
  "nome": "MÓVEL PAINEL CANALETADO",
  "preco": 620.00,
  "tamanho": "1.80m",
  "dimensoes": "1.80m Altura x 90cm Largura x 30cm Profundidade",
  "img": "./images/MOVELPAINEL (2).jpeg",
  "galeria": [
    "./images/MOVELPAINEL (3).jpeg",
    "./images/MOVELPAINEL (1).jpeg",
    "./images/MOVELPAINEL (2).jpeg"
  ],
  "descricao": "Móvel painel canaletado em MDF, ideal para exposição versátil com ganchos e acessórios, mantendo a organização e boa visualização dos produtos.\n\nAltura: 1.80m\nLargura: 90cm\nProfundidade: 30cm.",
  "tags": ["movel", "moveis", "painel canaletado", "canaletado", "expositor", "mdf", "loja", "organizador"]
 }
,
 {
  "id": 22,
  "categoria": ["Expositores", "Painel Canaletado", "Moveis"],
  "nome": "MÓVEL PAINEL COM NICHO LATERAL",
  "preco": 750.00,
  "tamanho": "1.80m",
  "dimensoes": "1.80m Altura x 90cm Largura x 30cm Profundidade",
  "img": "./images/painel.nicholat.jpeg",
  "galeria": [
    "./images/painel.nicholat.jpeg"
  ],
  "descricao": "Móvel painel com nicho lateral em MDF, ideal para organizar e destacar produtos com visual funcional e moderno.\n\nAltura: 1.80m\nLargura: 90cm\nProfundidade: 30cm.",
  "tags": ["movel", "moveis", "painel", "nicho lateral", "expositor", "mdf", "loja", "organizador"]
 },
 {
  "id": 23,
  "categoria": ["Expositores", "Painel Canaletado", "Moveis"],
  "nome": "MÓVEL PAINEL CANALETADO COM 9 NICHOS",
  "preco": 750.00,
  "tamanho": "1.80m",
  "dimensoes": "1.80m Altura x 90cm Largura x 30cm Profundidade",
  "img": "./images/painel9nichos.jpeg",
  "galeria": [
    "./images/painel9nichos.jpeg"
  ],
  "descricao": "Móvel painel canaletado com 9 nichos, ideal para exposição organizada e melhor aproveitamento vertical do espaço.\n\nAltura: 1.80m\nLargura: 90cm\nProfundidade: 30cm.",
  "tags": ["movel", "moveis", "painel canaletado", "9 nichos", "expositor", "mdf", "loja", "organizador"]
 },
 {
  "id": 24,
  "categoria": ["Expositores", "Painel Canaletado", "Moveis"],
  "nome": "MÓVEL PAINEL CANALETADO COM 6 NICHOS",
  "preco": 750.00,
  "tamanho": "1.80m",
  "dimensoes": "1.80m Altura x 90cm Largura x 30cm Profundidade",
  "img": "./images/painel6nichos.jpeg",
  "galeria": [
    "./images/painel6nichos.jpeg"
  ],
  "descricao": "Móvel painel canaletado com 6 nichos, ideal para exposição prática com organização e boa visualização dos produtos.\n\nAltura: 1.80m\nLargura: 90cm\nProfundidade: 30cm.",
  "tags": ["movel", "moveis", "painel canaletado", "6 nichos", "expositor", "mdf", "loja", "organizador"]
 }
,
 {
  "id": 25,
  "categoria": ["Araras", "Expositores", "Kits", "Moveis"],
  "nome": "KIT CABIDEIROS 60CM",
  "preco": 899.00,
  "tamanho": "1.80m",
  "dimensoes": "1.80m Altura x 60cm Largura x 30cm Profundidade (unitário) | 1.80m Altura x 1.80m Largura x 30cm Profundidade (kit)",
  "img": "./images/kit60cm (2).jpeg",
  "galeria": [
    "./images/kit60cm (2).jpeg",
    "./images/kit60cm (3).jpeg",
    "./images/kit60cm (4).jpeg",
    "./images/kit60cm (5).jpeg",
    "./images/kit60cm (1).jpeg"
  ],
  "descricao": "Kit com 3 móveis cabideiros de 60cm, ideal para montar uma parede expositora completa com ótimo aproveitamento de espaço. Valor do kit completo e único: R$ 899,00, em até 4x sem juros ou à vista, sem alteração de preço.\n\nMedidas unitárias:\nAltura: 1.80m\nLargura: 60cm\nProfundidade: 30cm.\n\nMedidas totais do kit:\nAltura: 1.80m\nLargura: 1.80m\nProfundidade: 30cm.",
  "tags": ["kit", "cabideiro", "cabideiros", "60cm", "arara", "expositor", "movel", "moveis", "loja"]
 }
]
